python_upgrade/__init__.py
python_upgrade/pyU.py
python_upgrade-10.3.dist-info/METADATA
python_upgrade-10.3.dist-info/WHEEL
python_upgrade-10.3.dist-info/top_level.txt
python_upgrade-10.3.dist-info/RECORD
