Metadata-Version: 2.1
Name: python-upgrade
Version: 10.3
Summary: Un module python contenant des fonctions plus avancées. Je l'ai conçu principalement pour la Numworks car elle n'a pas beaucoup de librairie.
Home-page: https://github.com/ZetaMap/Python_Upgrade
Author: ZetaMap
License: MIT
Project-URL: GitHub Project, https://github.com/ZetaMap/Python_Upgrade
Project-URL: My GitHub Page, https://github.com/ZetaMap/
Platform: UNKNOWN
Classifier: Programming Language :: Python :: 2
Classifier: Programming Language :: Python :: 3
Classifier: License :: OSI Approved :: MIT License
Classifier: Operating System :: Microsoft :: Windows
Classifier: Operating System :: Unix
Classifier: Operating System :: MacOS :: MacOS X
